{
  "version": 3,
  "middleware": {
    "/": {
      "files": [
        "server/edge/chunks/_9a10b88c._.js",
        "server/edge/chunks/node_modules_convex_dist_esm_0e0da4be._.js",
        "server/edge/chunks/node_modules_03775c48._.js",
        "server/edge/chunks/[root-of-the-server]__dc15d093._.js",
        "server/edge/chunks/edge-wrapper_cd125090.js"
      ],
      "name": "middleware",
      "page": "/",
      "matchers": [
        {
          "regexp": "^(?:\\/(_next\\/data\\/[^/]{1,}))?(?:\\/((?!.*\\..*|_next).*))(\\\\.json)?[\\/#\\?]?$",
          "originalSource": "/((?!.*\\..*|_next).*)"
        },
        {
          "regexp": "^(?:\\/(_next\\/data\\/[^/]{1,}))?(?:\\/(\\/?index|\\/?index\\\\.json))?[\\/#\\?]?$",
          "originalSource": "/"
        },
        {
          "regexp": "^(?:\\/(_next\\/data\\/[^/]{1,}))?(?:\\/(api|trpc))(.*)(\\\\.json)?[\\/#\\?]?$",
          "originalSource": "/(api|trpc)(.*)"
        }
      ],
      "wasm": [],
      "assets": [],
      "env": {
        "__NEXT_BUILD_ID": "development",
        "NEXT_SERVER_ACTIONS_ENCRYPTION_KEY": "GkAZhNedO6fbJsuBN+YbUzKQtBW/U3W000Oyt6KtATk=",
        "__NEXT_PREVIEW_MODE_ID": "aae9dbbfc39d538d1eb425ab57eb0c62",
        "__NEXT_PREVIEW_MODE_ENCRYPTION_KEY": "02ee4a55e224a0bacfa5018c858b3949086207bbae627818c210d27c5ad642aa",
        "__NEXT_PREVIEW_MODE_SIGNING_KEY": "837ed417dc37e53842af13e08928c9597dce5f170312f41e4fa03a1741da3986"
      }
    }
  },
  "sortedMiddleware": [
    "/"
  ],
  "functions": {}
}